[{"rank": 1, "name": "Jurgen", "date": "20-01-2024", "wpm": 52, "mistakes": 0}, {"rank": 2, "name": "Jurgen", "date": "20-01-2024", "wpm": 51, "mistakes": 0}, {"rank": 3, "name": "Unknown", "date": "01-01-2024", "wpm": 16, "mistakes": 0}, {"rank": 4, "name": "Unknown", "date": "01-01-2024", "wpm": 15, "mistakes": 0}, {"rank": 5, "name": "Unknown", "date": "01-01-2024", "wpm": 14, "mistakes": 0}, {"rank": 6, "name": "Unknown", "date": "01-01-2024", "wpm": 13, "mistakes": 0}, {"rank": 7, "name": "Unknown", "date": "01-01-2024", "wpm": 12, "mistakes": 0}, {"rank": 8, "name": "Unknown", "date": "01-01-2024", "wpm": 11, "mistakes": 0}, {"rank": 9, "name": "Unknown", "date": "01-01-2024", "wpm": 10, "mistakes": 0}, {"rank": 10, "name": "Jurgen", "date": "20-01-2024", "wpm": 10, "mistakes": 0}, {"rank": 11, "name": "Unknown", "date": "01-01-2024", "wpm": 9, "mistakes": 0}, {"rank": 12, "name": "Unknown", "date": "01-01-2024", "wpm": 8, "mistakes": 0}, {"rank": 13, "name": "Jurgen", "date": "20-01-2024", "wpm": 8, "mistakes": 5}, {"rank": 14, "name": "Unknown", "date": "01-01-2024", "wpm": 7, "mistakes": 0}, {"rank": 15, "name": "Unknown", "date": "01-01-2024", "wpm": 6, "mistakes": 0}]